src/__init__.py
src/app.py
src/student.py
elPlan_prueba_despliegues-0.1.4.dist-info/METADATA
elPlan_prueba_despliegues-0.1.4.dist-info/WHEEL
elPlan_prueba_despliegues-0.1.4.dist-info/entry_points.txt
elPlan_prueba_despliegues-0.1.4.dist-info/top_level.txt
elPlan_prueba_despliegues-0.1.4.dist-info/RECORD
